srpg/__init__.py
srpg-0.0.2.dist-info/LICENSE
srpg-0.0.2.dist-info/METADATA
srpg-0.0.2.dist-info/WHEEL
srpg-0.0.2.dist-info/top_level.txt
srpg-0.0.2.dist-info/RECORD
